list_difference/__init__.py
list_difference_zhuby1973-0.0.2.dist-info/LICENSE
list_difference_zhuby1973-0.0.2.dist-info/METADATA
list_difference_zhuby1973-0.0.2.dist-info/WHEEL
list_difference_zhuby1973-0.0.2.dist-info/top_level.txt
list_difference_zhuby1973-0.0.2.dist-info/RECORD
