Metadata-Version: 2.1
Name: list-difference-zhuby1973
Version: 0.0.2
Summary: A package to find difference between two list
Home-page: https://github.com/pypa/sampleproject
Author: Hans Zhu
Author-email: zhuby1973@gmail.com
License: UNKNOWN
Platform: UNKNOWN
Classifier: Programming Language :: Python :: 3
Classifier: License :: OSI Approved :: MIT License
Classifier: Operating System :: OS Independent
Requires-Python: >=3.6
